pwmodel/__init__.py
pwmodel/buildmodel.py
pwmodel/fast_fuzzysearch.py
pwmodel/helper.py
pwmodel/models.py
pwmodel/pwfile.py
pwmodels-1.2.data/scripts/buildmodel.py
pwmodels-1.2.dist-info/DESCRIPTION.rst
pwmodels-1.2.dist-info/METADATA
pwmodels-1.2.dist-info/RECORD
pwmodels-1.2.dist-info/WHEEL
pwmodels-1.2.dist-info/metadata.json
pwmodels-1.2.dist-info/top_level.txt
